django_sharded-0.1.2.dist-info/DESCRIPTION.rst
django_sharded-0.1.2.dist-info/METADATA
django_sharded-0.1.2.dist-info/RECORD
django_sharded-0.1.2.dist-info/WHEEL
django_sharded-0.1.2.dist-info/metadata.json
django_sharded-0.1.2.dist-info/top_level.txt
sharded/__init__.py
sharded/admin.py
sharded/exceptions.py
sharded/models.py
sharded/tests.py
sharded/views.py
sharded/db/__init__.py
sharded/db/routers.py
sharded/db/backends/__init__.py
sharded/db/backends/postgresql_psycopg2/__init__.py
sharded/db/backends/postgresql_psycopg2/base.py
sharded/db/models/__init__.py
sharded/db/models/fields.py
sharded/db/models/manager.py
sharded/db/models/query.py
sharded/management/__init__.py
sharded/management/commands/__init__.py
sharded/management/commands/initshard.py
sharded/management/commands/migrate.py
sharded/management/commands/updateshard.py
sharded/migrations/0001_initial.py
sharded/migrations/__init__.py
