Metadata-Version: 2.0
Name: django-sharded
Version: 0.1.2
Summary: Get started with sharded databases using ShardedModel, related fields, querysets, managers and a shard-aware database router.
Home-page: https://github.com/f0r4y312/django-sharded
Author: Vimal Aravindashan
Author-email: vimal.aravindashan@gmail.com
License: Apache-2.0
Keywords: django shards sharding sharded databases
Platform: any
Classifier: Environment :: Web Environment
Classifier: Framework :: Django
Classifier: Framework :: Django :: 1.8
Classifier: Intended Audience :: Developers
Classifier: License :: OSI Approved :: Apache Software License
Classifier: Operating System :: OS Independent
Classifier: Programming Language :: Python
Classifier: Programming Language :: Python :: 2
Classifier: Programming Language :: Python :: 2.7
Classifier: Topic :: Internet :: WWW/HTTP
Classifier: Topic :: Internet :: WWW/HTTP :: Dynamic Content
Requires-Dist: django (>=1.8,<2)
